{
  "conditions": [
    {
      "type": "forge:mod_loaded",
      "modid": "brewinandchewin"
    }
  ],
  "type": "brewinandchewin:fermenting",
  "basefluid": {
    "count": 500,
    "fluid": "minecraft:water"
  },
  "experience": 1.0,
  "ingredients": [
    {
      "item": "hearthandharvest:green_grapes"
    },
    {
      "item": "hearthandharvest:green_grapes"
    },
    {
      "item": "minecraft:sugar"
    },
    []
  ],
  "recipe_book_tab": "drinks",
  "result": {
    "count": 500,
    "fluid": "hearthandharvest:green_grape_wine"
  }
}